bitwarden.py
awsume_bitwarden_plugin-0.0.1.dist-info/LICENSE
awsume_bitwarden_plugin-0.0.1.dist-info/METADATA
awsume_bitwarden_plugin-0.0.1.dist-info/WHEEL
awsume_bitwarden_plugin-0.0.1.dist-info/entry_points.txt
awsume_bitwarden_plugin-0.0.1.dist-info/top_level.txt
awsume_bitwarden_plugin-0.0.1.dist-info/RECORD
