Metadata-Version: 2.1
Name: awsume-bitwarden-plugin
Version: 0.0.1
Summary: a small helper for awsume and bitwarden
Author-email: Daniel Jensen <daniel+pypi@d-jensen.de>
Project-URL: Homepage, https://github.com/danto7/awsume-bitwarden-plugin
Project-URL: Bug Tracker, https://github.com/danto7/awsume-bitwarden-plugin/issues
Classifier: Programming Language :: Python :: 3
Classifier: License :: OSI Approved :: MIT License
Classifier: Operating System :: OS Independent
Requires-Python: >=3.8
License-File: LICENSE
Requires-Dist: awsume (>=4)
